dff.v
module dff(clk, q, qbar, d);
    input clk;
    output q, qbar;
    reg q, qbar;
    input d;

    always @(posedge clk) 
    begin
        if (d == 1'b0 || d ==1'b1)
        begin
            q = d;
        end
        else
        begin
            q = 1'b0;
        end
        qbar = ~q;
    end
endmodule

counter.v
module counter(clk, count , RCO);
    input clk;
    output [0:3]count;
    output RCO;
    wire D0, D1, D3, D4, Q0B, Q1B, Q2B, Q3B, A1, A2;

    dff dff0(.clk(clk), .q(count[3]), .qbar(Q0B), .d(Q0B));
    dff dff1(.clk(Q0B), .q(count[2]), .qbar(Q1B), .d(Q1B));
    dff dff2(.clk(Q1B), .q(count[1]), .qbar(Q2B), .d(Q2B));
    dff dff3(.clk(Q2B), .q(count[0]), .qbar(Q3B), .d(Q3B));

    and And_1(A1, count[0], count[1], count[2], count[3]);
    nor And_2(A2, count[0], count[1], count[2], count[3]);

    or Or_01(RCO, A1, A2);
endmodule

counter_tb.v
`timescale 1ns/1ns
module counter_tb;
    wire RCO;
    wire [0:3]count;
    reg clk;

    initial
    begin
       $dumpfile("counter_tb.vcd");
       $dumpvars(0, counter_tb); 
    end

    counter uut(clk, count, RCO);
    always #5 clk = ~clk;

    initial
    begin
        clk = 1'b1;
        #5;
        //repeat (1) @ (posedge clk);
        repeat (30) @ (posedge clk);
        $finish;
    end
endmodule

counter_tb.vcd
$date
	Tue May 11 22:36:02 2021
$end
$version
	Icarus Verilog
$end
$timescale
	1ns
$end
$scope module counter_tb $end
$var wire 4 ! count [0:3] $end
$var wire 1 " RCO $end
$var reg 1 # clk $end
$scope module uut $end
$var wire 1 $ A1 $end
$var wire 1 % A2 $end
$var wire 1 " RCO $end
$var wire 1 # clk $end
$var wire 4 & count [0:3] $end
$var wire 1 ' Q3B $end
$var wire 1 ( Q2B $end
$var wire 1 ) Q1B $end
$var wire 1 * Q0B $end
$scope module dff0 $end
$var wire 1 # clk $end
$var wire 1 * d $end
$var reg 1 + q $end
$var reg 1 * qbar $end
$upscope $end
$scope module dff1 $end
$var wire 1 * clk $end
$var wire 1 ) d $end
$var reg 1 , q $end
$var reg 1 ) qbar $end
$upscope $end
$scope module dff2 $end
$var wire 1 ) clk $end
$var wire 1 ( d $end
$var reg 1 - q $end
$var reg 1 ( qbar $end
$upscope $end
$scope module dff3 $end
$var wire 1 ( clk $end
$var wire 1 ' d $end
$var reg 1 . q $end
$var reg 1 ' qbar $end
$upscope $end
$upscope $end
$upscope $end
$enddefinitions $end
#0
$dumpvars
0.
0-
0,
0+
1*
1)
1(
1'
b0 &
1%
0$
1#
1"
b0 !
$end
#5
0#
#10
0"
0%
0*
b1 !
b1 &
1+
1#
#15
0#
#20
0"
0%
0)
1,
1*
b10 !
b10 &
0+
1#
#25
0#
#30
0*
b11 !
b11 &
1+
1#
#35
0#
#40
0"
0%
0(
1-
1)
0,
1*
b100 !
b100 &
0+
1#
#45
0#
#50
0*
b101 !
b101 &
1+
1#
#55
0#
#60
0)
1,
1*
b110 !
b110 &
0+
1#
#65
0#
#70
0*
b111 !
b111 &
1+
1#
#75
0#
#80
0"
0%
0'
1.
1(
0-
1)
0,
1*
b1000 !
b1000 &
0+
1#
#85
0#
#90
0*
b1001 !
b1001 &
1+
1#
#95
0#
#100
0)
1,
1*
b1010 !
b1010 &
0+
1#
#105
0#
#110
0*
b1011 !
b1011 &
1+
1#
#115
0#
#120
0(
1-
1)
0,
1*
b1100 !
b1100 &
0+
1#
#125
0#
#130
0*
b1101 !
b1101 &
1+
1#
#135
0#
#140
0)
1,
1*
b1110 !
b1110 &
0+
1#
#145
0#
#150
1"
1$
0*
b1111 !
b1111 &
1+
1#
#155
0#
#160
1%
1'
0.
1"
1(
0-
0$
1)
0,
1*
b0 !
b0 &
0+
1#
#165
0#
#170
0"
0%
0*
b1 !
b1 &
1+
1#
#175
0#
#180
0"
0%
0)
1,
1*
b10 !
b10 &
0+
1#
#185
0#
#190
0*
b11 !
b11 &
1+
1#
#195
0#
#200
0"
0%
0(
1-
1)
0,
1*
b100 !
b100 &
0+
1#
#205
0#
#210
0*
b101 !
b101 &
1+
1#
#215
0#
#220
0)
1,
1*
b110 !
b110 &
0+
1#
#225
0#
#230
0*
b111 !
b111 &
1+
1#
#235
0#
#240
0"
0%
0'
1.
1(
0-
1)
0,
1*
b1000 !
b1000 &
0+
1#
#245
0#
#250
0*
b1001 !
b1001 &
1+
1#
#255
0#
#260
0)
1,
1*
b1010 !
b1010 &
0+
1#
#265
0#
#270
0*
b1011 !
b1011 &
1+
1#
#275
0#
#280
0(
1-
1)
0,
1*
b1100 !
b1100 &
0+
1#
#285
0#
#290
0*
b1101 !
b1101 &
1+
1#
#295
0#
#300
0)
1,
1*
b1110 !
b1110 &
0+
1#
