dff.v
module dff(clk, q, qbar, d);
    input clk;
    output q, qbar;
    reg q, qbar;
    input d;

    always @(posedge clk) 
    begin
        if (d == 1'b0 || d ==1'b1)
        begin
            q = d;
        end
        else
        begin
            q = 1'b0;
        end
        qbar = ~q;
   end
endmodule

dff_tb.v
`timescale 1ns/1ns
module dff_tb;
    reg clk, d, reset;
    wire q, qbar;

    initial
    begin
        $dumpfile("dff_tb.vcd");
        $dumpvars(0, dff_tb);
    end

    dff flipflop(clk, q, qbar, d);
    always #5 clk = ~clk;

    initial begin
        reset <= 1'b1;
        clk <= 1'b0;
        d <= 1'b0;
        repeat (20) @ (posedge clk)
        begin
            d = ~d;
            #5;
        end
        $finish;
    end
endmodule

dff_tb.vcd
$date
	Fri May 14 17:20:40 2021
$end
$version
	Icarus Verilog
$end
$timescale
	1ns
$end
$scope module dff_tb $end
$var wire 1 ! qbar $end
$var wire 1 " q $end
$var reg 1 # clk $end
$var reg 1 $ d $end
$var reg 1 % reset $end
$scope module flipflop $end
$var wire 1 # clk $end
$var wire 1 $ d $end
$var reg 1 " q $end
$var reg 1 ! qbar $end
$upscope $end
$upscope $end
$enddefinitions $end
#0
$dumpvars
1%
0$
0#
x"
x!
$end
#5
0!
1"
1$
1#
#10
0#
#15
1!
0"
0$
1#
#20
0#
#25
0!
1"
1$
1#
#30
0#
#35
1!
0"
0$
1#
#40
0#
#45
0!
1"
1$
1#
#50
0#
#55
1!
0"
0$
1#
#60
0#
#65
0!
1"
1$
1#
#70
0#
#75
1!
0"
0$
1#
#80
0#
#85
0!
1"
1$
1#
#90
0#
#95
1!
0"
0$
1#
#100
0#
#105
0!
1"
1$
1#
#110
0#
#115
1!
0"
0$
1#
#120
0#
#125
0!
1"
1$
1#
#130
0#
#135
1!
0"
0$
1#
#140
0#
#145
0!
1"
1$
1#
#150
0#
#155
1!
0"
0$
1#
#160
0#
#165
0!
1"
1$
1#
#170
0#
#175
1!
0"
0$
1#
#180
0#
#185
0!
1"
1$
1#
#190
0#
#195
1!
0"
0$
1#
